cellograph/__init__.py
cellograph/cellograph.py
cellograph-0.0.6.dist-info/LICENSE
cellograph-0.0.6.dist-info/METADATA
cellograph-0.0.6.dist-info/WHEEL
cellograph-0.0.6.dist-info/top_level.txt
cellograph-0.0.6.dist-info/RECORD
